buienradar/__init__.py
buienradar/__main__.py
buienradar/buienradar.py
buienradar/buienradar_json.py
buienradar/buienradar_xml.py
buienradar/constants.py
buienradar/urls.py
buienradar-1.0.6.dist-info/LICENSE
buienradar-1.0.6.dist-info/METADATA
buienradar-1.0.6.dist-info/WHEEL
buienradar-1.0.6.dist-info/entry_points.txt
buienradar-1.0.6.dist-info/top_level.txt
buienradar-1.0.6.dist-info/RECORD
