Metadata-Version: 2.1
Name: buienradar
Version: 1.0.6
Summary: Library and CLI tools for interacting with buienradar.
Home-page: https://github.com/mjj4791/python-buienradar
Author: mjj4791
Author-email: 
License: MIT
Keywords: buienradar weather
Classifier: Development Status :: 5 - Production/Stable
Classifier: Intended Audience :: Developers
Classifier: License :: OSI Approved :: MIT License
Classifier: Programming Language :: Python :: 3.4
Classifier: Programming Language :: Python :: 3.5
Classifier: Programming Language :: Python :: 3.6
Classifier: Programming Language :: Python :: 3.7
Classifier: Programming Language :: Python :: 3.8
Classifier: Programming Language :: Python :: 3.11
Classifier: Programming Language :: Python :: 3.12
License-File: LICENSE
Requires-Dist: docopt
Requires-Dist: pytz
Requires-Dist: requests
Requires-Dist: xmltodict
Requires-Dist: vincenty
